{
  "FinalHFR": 2.5980096683268807,
  "Region": null,
  "HocusFocusStarDetectionOptions": {
    "DebugMode": false,
    "UseAdvanced": false,
    "ModelPSF": true,
    "StarMeasurementNoiseReductionEnabled": false,
    "PSFFitType": 0,
    "Simple_NoiseLevel": 0,
    "Simple_PixelScale": 0,
    "Simple_FocusRange": 0,
    "HotpixelFiltering": true,
    "HotpixelThresholdingEnabled": true,
    "UseAutoFocusCrop": true,
    "NoiseReductionRadius": 4,
    "NoiseClippingMultiplier": 4.0,
    "StarClippingMultiplier": 2.0,
    "StructureLayers": 4,
    "StarCenterTolerance": 0.3,
    "StarPeakResponse": 0.75,
    "MaxDistortion": 0.5,
    "BrightnessSensitivity": 10.0,
    "StarBackgroundBoxExpansion": 3,
    "MinStarBoundingBoxSize": 5,
    "MinHFR": 1.5,
    "StructureDilationSize": 3,
    "StructureDilationCount": 0,
    "PixelSampleSize": 1.0,
    "IntermediateSavePath": "C:\\Users\\nicka\\AppData\\Local\\NINA\\HocusFocusIntermediate",
    "SaveIntermediateImages": false,
    "PSFParallelPartitionSize": 100,
    "PSFResolution": 10,
    "PSFFitThreshold": 0.9,
    "UsePSFAbsoluteDeviation": false,
    "HotpixelThreshold": 0.001,
    "SaturationThreshold": 0.99,
    "MeasurementAverage": 0
  },
  "HocusFocusAutoFocusOptions": {
    "MaxConcurrent": 0,
    "FastFocusModeEnabled": false,
    "FastStepSize": 1,
    "FastOffsetSteps": 4,
    "FastThreshold_Seconds": 3600,
    "FastThreshold_Celcius": 5,
    "FastThreshold_FocuserPosition": 100,
    "ValidateHfrImprovement": true,
    "HFRImprovementThreshold": 0.15,
    "AutoFocusTimeoutSeconds": 600,
    "SavePath": "C:\\Users\\nicka\\Documents\\NINA-AF-Images",
    "Save": false,
    "LastSelectedLoadPath": "",
    "FocuserOffset": 0,
    "MaxOutlierRejections": 1,
    "OutlierRejectionConfidence": 0.9,
    "UnevenHyperbolicFitEnabled": true,
    "WeightedHyperbolicFitEnabled": true
  },
  "FocuserOptions": {
    "Id": "ASCOM.EAF.Focuser",
    "LastDeviceName": "ZWO Focuser (ASCOM)",
    "UseFilterWheelOffsets": true,
    "AutoFocusStepSize": 23,
    "AutoFocusInitialOffsetSteps": 6,
    "AutoFocusExposureTime": 3.0,
    "AutoFocusMethod": 0,
    "ContrastDetectionMethod": 2,
    "AutoFocusDisableGuiding": true,
    "FocuserSettleTime": 1,
    "AutoFocusTotalNumberOfAttempts": 1,
    "AutoFocusNumberOfFramesPerPoint": 1,
    "AutoFocusInnerCropRatio": 1.0,
    "AutoFocusOuterCropRatio": 1.0,
    "BacklashIn": 300,
    "BacklashOut": 0,
    "AutoFocusBinning": 1,
    "AutoFocusUseBrightestStars": 0,
    "AutoFocusCurveFitting": 3,
    "BacklashCompensationModel": 1,
    "AutoFocusTimeoutSeconds": 600,
    "RSquaredThreshold": 0.7
  },
  "Version": 2,
  "Filter": "L",
  "AutoFocuserName": "Hocus Focus",
  "StarDetectorName": "Hocus Focus",
  "Timestamp": "2025-10-20T06:41:06.1910681-05:00",
  "Temperature": 19.670000076293945,
  "Method": "STARHFR",
  "Fitting": "HYPERBOLIC",
  "InitialFocusPoint": {
    "Position": 386355.0,
    "Value": 2.738665460830257,
    "Error": 0.0
  },
  "CalculatedFocusPoint": {
    "Position": 386352.5662561619,
    "Value": 2.630739481537204,
    "Error": 0.0
  },
  "PreviousFocusPoint": {
    "Position": 386352.5662561619,
    "Value": 2.630739481537204,
    "Error": 0.0
  },
  "MeasurePoints": [
    {
      "Position": 386217.0,
      "Value": 7.433220050449258,
      "Error": 0.26704262352628216
    },
    {
      "Position": 386240.0,
      "Value": 6.376976863056601,
      "Error": 0.3089063838034187
    },
    {
      "Position": 386263.0,
      "Value": 5.166154549349972,
      "Error": 0.3734506466047218
    },
    {
      "Position": 386286.0,
      "Value": 4.139841194542648,
      "Error": 0.37509948486911693
    },
    {
      "Position": 386309.0,
      "Value": 3.273789295208303,
      "Error": 0.4076899193646404
    },
    {
      "Position": 386332.0,
      "Value": 2.8135661621491743,
      "Error": 0.31295911526031617
    },
    {
      "Position": 386355.0,
      "Value": 2.6453933815145887,
      "Error": 0.25637498016666127
    },
    {
      "Position": 386378.0,
      "Value": 2.7320388978035433,
      "Error": 0.32523242010148756
    },
    {
      "Position": 386401.0,
      "Value": 2.728204956243795,
      "Error": 0.32910932117412406
    },
    {
      "Position": 386424.0,
      "Value": 3.210942205353577,
      "Error": 0.491558395755213
    },
    {
      "Position": 386447.0,
      "Value": 3.2159755854378673,
      "Error": 0.6179806380448674
    },
    {
      "Position": 386470.0,
      "Value": 3.5940805104398312,
      "Error": 0.7409400415701071
    },
    {
      "Position": 386493.0,
      "Value": 4.302912127444593,
      "Error": 0.938885036408887
    }
  ],
  "Intersections": {
    "TrendLineIntersection": {
      "Position": 386344.0,
      "Value": 2.0492797578808677,
      "Error": 0.0
    },
    "HyperbolicMinimum": {
      "Position": 386352.5662561619,
      "Value": 2.630739481537204,
      "Error": 0.0
    },
    "QuadraticMinimum": null,
    "GaussianMaximum": null
  },
  "Fittings": {
    "Quadratic": "",
    "Hyperbolic": "y = min(max(0, (386352.566 - x) / 23), 1) * 4.382/73.188 * √((x - 386352.566)² + 73.188²) + (1 - min(max(0, (386352.566 - x) / 23), 1)) * 4.382/158.926 * √((x - 386352.566)² + 158.926²) + -1.751",
    "Gaussian": "",
    "LeftTrend": "y = -0.04148781628385604 * x + 16030.601967143462",
    "RightTrend": "y = 0.013191837175547267 * x + -5094.532708673988"
  },
  "RSquares": {
    "Quadratic": "NaN",
    "Hyperbolic": 0.9975158889848978,
    "LeftTrend": 0.9864492032649118,
    "RightTrend": 0.7865017460304722
  },
  "BacklashCompensation": {
    "BacklashCompensationModel": "OVERSHOOT",
    "BacklashIN": 300,
    "BacklashOUT": 0
  },
  "Duration": "00:03:18.1671263"
}