{
  "$id": "1",
  "$type": "NINA.Sequencer.Container.SequenceRootContainer, NINA.Sequencer",
  "Strategy": {
    "$type": "NINA.Sequencer.Container.ExecutionStrategy.SequentialStrategy, NINA.Sequencer"
  },
  "Name": "Panel1-H",
  "Conditions": {
    "$id": "2",
    "$type": "System.Collections.ObjectModel.ObservableCollection`1[[NINA.Sequencer.Conditions.ISequenceCondition, NINA.Sequencer]], System.ObjectModel",
    "$values": []
  },
  "IsExpanded": true,
  "Items": {
    "$id": "3",
    "$type": "System.Collections.ObjectModel.ObservableCollection`1[[NINA.Sequencer.SequenceItem.ISequenceItem, NINA.Sequencer]], System.ObjectModel",
    "$values": [
      {
        "$id": "4",
        "$type": "NINA.Sequencer.Container.StartAreaContainer, NINA.Sequencer",
        "Strategy": {
          "$type": "NINA.Sequencer.Container.ExecutionStrategy.SequentialStrategy, NINA.Sequencer"
        },
        "Name": "Start",
        "Conditions": {
          "$id": "5",
          "$type": "System.Collections.ObjectModel.ObservableCollection`1[[NINA.Sequencer.Conditions.ISequenceCondition, NINA.Sequencer]], System.ObjectModel",
          "$values": []
        },
        "IsExpanded": true,
        "Items": {
          "$id": "6",
          "$type": "System.Collections.ObjectModel.ObservableCollection`1[[NINA.Sequencer.SequenceItem.ISequenceItem, NINA.Sequencer]], System.ObjectModel",
          "$values": [
            {
              "$id": "7",
              "$type": "NINA.Sequencer.Container.SequentialContainer, NINA.Sequencer",
              "Strategy": {
                "$type": "NINA.Sequencer.Container.ExecutionStrategy.SequentialStrategy, NINA.Sequencer"
              },
              "Name": "Wait",
              "Conditions": {
                "$id": "8",
                "$type": "System.Collections.ObjectModel.ObservableCollection`1[[NINA.Sequencer.Conditions.ISequenceCondition, NINA.Sequencer]], System.ObjectModel",
                "$values": []
              },
              "IsExpanded": true,
              "Items": {
                "$id": "9",
                "$type": "System.Collections.ObjectModel.ObservableCollection`1[[NINA.Sequencer.SequenceItem.ISequenceItem, NINA.Sequencer]], System.ObjectModel",
                "$values": [
                  {
                    "$id": "10",
                    "$type": "NINA.Sequencer.SequenceItem.Utility.WaitForTime, NINA.Sequencer",
                    "Hours": 20,
                    "Minutes": 31,
                    "MinutesOffset": -60,
                    "Seconds": 58,
                    "SelectedProvider": {
                      "$id": "11",
                      "$type": "NINA.Sequencer.Utility.DateTimeProvider.NauticalDuskProvider, NINA.Sequencer"
                    },
                    "Parent": {
                      "$ref": "7"
                    },
                    "ErrorBehavior": 0,
                    "Attempts": 1
                  },
                  {
                    "$id": "12",
                    "$type": "NINA.Plugins.Connector.Instructions.ConnectAllEquipment, NINA.Plugins.Connector",
                    "Parent": {
                      "$ref": "7"
                    },
                    "ErrorBehavior": 0,
                    "Attempts": 1
                  }
                ]
              },
              "Triggers": {
                "$id": "13",
                "$type": "System.Collections.ObjectModel.ObservableCollection`1[[NINA.Sequencer.Trigger.ISequenceTrigger, NINA.Sequencer]], System.ObjectModel",
                "$values": []
              },
              "Parent": {
                "$ref": "4"
              },
              "ErrorBehavior": 0,
              "Attempts": 1
            },
            {
              "$id": "14",
              "$type": "NINA.Sequencer.Container.ParallelContainer, NINA.Sequencer",
              "Strategy": {
                "$type": "NINA.Sequencer.Container.ExecutionStrategy.ParallelStrategy, NINA.Sequencer"
              },
              "Name": "Startup 0 C",
              "Conditions": {
                "$id": "15",
                "$type": "System.Collections.ObjectModel.ObservableCollection`1[[NINA.Sequencer.Conditions.ISequenceCondition, NINA.Sequencer]], System.ObjectModel",
                "$values": []
              },
              "IsExpanded": true,
              "Items": {
                "$id": "16",
                "$type": "System.Collections.ObjectModel.ObservableCollection`1[[NINA.Sequencer.SequenceItem.ISequenceItem, NINA.Sequencer]], System.ObjectModel",
                "$values": [
                  {
                    "$id": "17",
                    "$type": "NINA.Sequencer.SequenceItem.Telescope.FindHome, NINA.Sequencer",
                    "Parent": {
                      "$ref": "14"
                    },
                    "ErrorBehavior": 0,
                    "Attempts": 1
                  },
                  {
                    "$id": "18",
                    "$type": "NINA.Sequencer.SequenceItem.Camera.CoolCamera, NINA.Sequencer",
                    "Temperature": 0.0,
                    "Duration": 0.0,
                    "Parent": {
                      "$ref": "14"
                    },
                    "ErrorBehavior": 0,
                    "Attempts": 1
                  },
                  {
                    "$id": "19",
                    "$type": "NINA.Sequencer.SequenceItem.Utility.WaitForTime, NINA.Sequencer",
                    "Hours": 21,
                    "Minutes": 31,
                    "MinutesOffset": 0,
                    "Seconds": 58,
                    "SelectedProvider": {
                      "$ref": "11"
                    },
                    "Parent": {
                      "$ref": "14"
                    },
                    "ErrorBehavior": 0,
                    "Attempts": 1
                  }
                ]
              },
              "Triggers": {
                "$id": "20",
                "$type": "System.Collections.ObjectModel.ObservableCollection`1[[NINA.Sequencer.Trigger.ISequenceTrigger, NINA.Sequencer]], System.ObjectModel",
                "$values": []
              },
              "Parent": {
                "$ref": "4"
              },
              "ErrorBehavior": 0,
              "Attempts": 1
            }
          ]
        },
        "Triggers": {
          "$id": "21",
          "$type": "System.Collections.ObjectModel.ObservableCollection`1[[NINA.Sequencer.Trigger.ISequenceTrigger, NINA.Sequencer]], System.ObjectModel",
          "$values": []
        },
        "Parent": {
          "$ref": "1"
        },
        "ErrorBehavior": 0,
        "Attempts": 1
      },
      {
        "$id": "22",
        "$type": "NINA.Sequencer.Container.TargetAreaContainer, NINA.Sequencer",
        "Strategy": {
          "$type": "NINA.Sequencer.Container.ExecutionStrategy.SequentialStrategy, NINA.Sequencer"
        },
        "Name": "Targets",
        "Conditions": {
          "$id": "23",
          "$type": "System.Collections.ObjectModel.ObservableCollection`1[[NINA.Sequencer.Conditions.ISequenceCondition, NINA.Sequencer]], System.ObjectModel",
          "$values": []
        },
        "IsExpanded": true,
        "Items": {
          "$id": "24",
          "$type": "System.Collections.ObjectModel.ObservableCollection`1[[NINA.Sequencer.SequenceItem.ISequenceItem, NINA.Sequencer]], System.ObjectModel",
          "$values": [
            {
              "$id": "25",
              "$type": "NINA.Sequencer.Container.SequentialContainer, NINA.Sequencer",
              "Strategy": {
                "$type": "NINA.Sequencer.Container.ExecutionStrategy.SequentialStrategy, NINA.Sequencer"
              },
              "Name": "H",
              "Conditions": {
                "$id": "26",
                "$type": "System.Collections.ObjectModel.ObservableCollection`1[[NINA.Sequencer.Conditions.ISequenceCondition, NINA.Sequencer]], System.ObjectModel",
                "$values": [
                  {
                    "$id": "27",
                    "$type": "NINA.Sequencer.Conditions.TimeCondition, NINA.Sequencer",
                    "Hours": 5,
                    "Minutes": 56,
                    "MinutesOffset": 0,
                    "Seconds": 2,
                    "SelectedProvider": {
                      "$id": "28",
                      "$type": "NINA.Sequencer.Utility.DateTimeProvider.NauticalDawnProvider, NINA.Sequencer"
                    },
                    "Parent": {
                      "$ref": "25"
                    }
                  }
                ]
              },
              "IsExpanded": true,
              "Items": {
                "$id": "29",
                "$type": "System.Collections.ObjectModel.ObservableCollection`1[[NINA.Sequencer.SequenceItem.ISequenceItem, NINA.Sequencer]], System.ObjectModel",
                "$values": [
                  {
                    "$id": "30",
                    "$type": "NINA.Sequencer.Container.DeepSkyObjectContainer, NINA.Sequencer",
                    "Target": {
                      "$id": "31",
                      "$type": "NINA.Astrometry.InputTarget, NINA.Astrometry",
                      "Expanded": true,
                      "TargetName": "LDN 1235 Panel 1",
                      "PositionAngle": 90.0,
                      "InputCoordinates": {
                        "$id": "32",
                        "$type": "NINA.Astrometry.InputCoordinates, NINA.Astrometry",
                        "RAHours": 22,
                        "RAMinutes": 30,
                        "RASeconds": 16.10427,
                        "NegativeDec": false,
                        "DecDegrees": 69,
                        "DecMinutes": 39,
                        "DecSeconds": 43.42609
                      }
                    },
                    "ExposureInfoListExpanded": false,
                    "ExposureInfoList": {
                      "$id": "33",
                      "$type": "NINA.Core.Utility.AsyncObservableCollection`1[[NINA.Sequencer.Utility.ExposureInfo, NINA.Sequencer]], NINA.Core",
                      "$values": []
                    },
                    "Strategy": {
                      "$type": "NINA.Sequencer.Container.ExecutionStrategy.SequentialStrategy, NINA.Sequencer"
                    },
                    "Name": "LDN 1235 Panel 1",
                    "Conditions": {
                      "$id": "34",
                      "$type": "System.Collections.ObjectModel.ObservableCollection`1[[NINA.Sequencer.Conditions.ISequenceCondition, NINA.Sequencer]], System.ObjectModel",
                      "$values": []
                    },
                    "IsExpanded": true,
                    "Items": {
                      "$id": "35",
                      "$type": "System.Collections.ObjectModel.ObservableCollection`1[[NINA.Sequencer.SequenceItem.ISequenceItem, NINA.Sequencer]], System.ObjectModel",
                      "$values": [
                        {
                          "$id": "36",
                          "$type": "NINA.Sequencer.SequenceItem.Platesolving.Center, NINA.Sequencer",
                          "Inherited": true,
                          "Coordinates": {
                            "$id": "37",
                            "$type": "NINA.Astrometry.InputCoordinates, NINA.Astrometry",
                            "RAHours": 22,
                            "RAMinutes": 30,
                            "RASeconds": 16.10427,
                            "NegativeDec": false,
                            "DecDegrees": 69,
                            "DecMinutes": 39,
                            "DecSeconds": 43.42609
                          },
                          "Parent": {
                            "$ref": "30"
                          },
                          "ErrorBehavior": 0,
                          "Attempts": 1
                        },
                        {
                          "$id": "38",
                          "$type": "NINA.Sequencer.SequenceItem.FilterWheel.SwitchFilter, NINA.Sequencer",
                          "Filter": {
                            "$id": "39",
                            "$type": "NINA.Core.Model.Equipment.FilterInfo, NINA.Core",
                            "_name": "L",
                            "_focusOffset": 0,
                            "_position": 0,
                            "_autoFocusExposureTime": 3.0,
                            "_autoFocusFilter": false,
                            "FlatWizardFilterSettings": {
                              "$id": "40",
                              "$type": "NINA.Core.Model.Equipment.FlatWizardFilterSettings, NINA.Core",
                              "FlatWizardMode": 0,
                              "HistogramMeanTarget": 0.5,
                              "HistogramTolerance": 0.1,
                              "MaxFlatExposureTime": 3.0,
                              "MinFlatExposureTime": 0.1,
                              "MaxAbsoluteFlatDeviceBrightness": 32767,
                              "MinAbsoluteFlatDeviceBrightness": 0,
                              "Gain": -1,
                              "Offset": -1,
                              "Binning": {
                                "$id": "41",
                                "$type": "NINA.Core.Model.Equipment.BinningMode, NINA.Core",
                                "X": 1,
                                "Y": 1
                              }
                            },
                            "_autoFocusBinning": {
                              "$id": "42",
                              "$type": "NINA.Core.Model.Equipment.BinningMode, NINA.Core",
                              "X": 1,
                              "Y": 1
                            },
                            "_autoFocusGain": 300,
                            "_autoFocusOffset": -1
                          },
                          "Parent": {
                            "$ref": "30"
                          },
                          "ErrorBehavior": 0,
                          "Attempts": 1
                        },
                        {
                          "$id": "43",
                          "$type": "NINA.Sequencer.SequenceItem.Autofocus.RunAutofocus, NINA.Sequencer",
                          "Parent": {
                            "$ref": "30"
                          },
                          "ErrorBehavior": 0,
                          "Attempts": 1
                        },
                        {
                          "$id": "44",
                          "$type": "NINA.Sequencer.SequenceItem.Guider.StartGuiding, NINA.Sequencer",
                          "ForceCalibration": false,
                          "Parent": {
                            "$ref": "30"
                          },
                          "ErrorBehavior": 0,
                          "Attempts": 1
                        },
                        {
                          "$id": "45",
                          "$type": "NINA.Sequencer.Container.SequentialContainer, NINA.Sequencer",
                          "Strategy": {
                            "$type": "NINA.Sequencer.Container.ExecutionStrategy.SequentialStrategy, NINA.Sequencer"
                          },
                          "Name": "Sequential Instruction Set",
                          "Conditions": {
                            "$id": "46",
                            "$type": "System.Collections.ObjectModel.ObservableCollection`1[[NINA.Sequencer.Conditions.ISequenceCondition, NINA.Sequencer]], System.ObjectModel",
                            "$values": []
                          },
                          "IsExpanded": true,
                          "Items": {
                            "$id": "47",
                            "$type": "System.Collections.ObjectModel.ObservableCollection`1[[NINA.Sequencer.SequenceItem.ISequenceItem, NINA.Sequencer]], System.ObjectModel",
                            "$values": [
                              {
                                "$id": "48",
                                "$type": "NINA.Sequencer.SequenceItem.Imaging.SmartExposure, NINA.Sequencer",
                                "ErrorBehavior": 0,
                                "Attempts": 1,
                                "Strategy": {
                                  "$type": "NINA.Sequencer.Container.ExecutionStrategy.SequentialStrategy, NINA.Sequencer"
                                },
                                "Name": "Smart Exposure",
                                "Conditions": {
                                  "$id": "49",
                                  "$type": "System.Collections.ObjectModel.ObservableCollection`1[[NINA.Sequencer.Conditions.ISequenceCondition, NINA.Sequencer]], System.ObjectModel",
                                  "$values": [
                                    {
                                      "$id": "50",
                                      "$type": "NINA.Sequencer.Conditions.LoopCondition, NINA.Sequencer",
                                      "CompletedIterations": 0,
                                      "Iterations": 1,
                                      "Parent": {
                                        "$ref": "48"
                                      }
                                    }
                                  ]
                                },
                                "IsExpanded": false,
                                "Items": {
                                  "$id": "51",
                                  "$type": "System.Collections.ObjectModel.ObservableCollection`1[[NINA.Sequencer.SequenceItem.ISequenceItem, NINA.Sequencer]], System.ObjectModel",
                                  "$values": [
                                    {
                                      "$id": "52",
                                      "$type": "NINA.Sequencer.SequenceItem.FilterWheel.SwitchFilter, NINA.Sequencer",
                                      "Filter": {
                                        "$id": "53",
                                        "$type": "NINA.Core.Model.Equipment.FilterInfo, NINA.Core",
                                        "_name": "H",
                                        "_focusOffset": 0,
                                        "_position": 5,
                                        "_autoFocusExposureTime": 15.0,
                                        "_autoFocusFilter": false,
                                        "FlatWizardFilterSettings": {
                                          "$id": "54",
                                          "$type": "NINA.Core.Model.Equipment.FlatWizardFilterSettings, NINA.Core",
                                          "FlatWizardMode": 0,
                                          "HistogramMeanTarget": 0.5,
                                          "HistogramTolerance": 0.1,
                                          "MaxFlatExposureTime": 30.0,
                                          "MinFlatExposureTime": 0.01,
                                          "MaxAbsoluteFlatDeviceBrightness": 1,
                                          "MinAbsoluteFlatDeviceBrightness": 0,
                                          "Gain": -1,
                                          "Offset": -1,
                                          "Binning": {
                                            "$id": "55",
                                            "$type": "NINA.Core.Model.Equipment.BinningMode, NINA.Core",
                                            "X": 1,
                                            "Y": 1
                                          }
                                        },
                                        "_autoFocusBinning": {
                                          "$id": "56",
                                          "$type": "NINA.Core.Model.Equipment.BinningMode, NINA.Core",
                                          "X": 1,
                                          "Y": 1
                                        },
                                        "_autoFocusGain": 300,
                                        "_autoFocusOffset": -1
                                      },
                                      "Parent": {
                                        "$ref": "48"
                                      },
                                      "ErrorBehavior": 0,
                                      "Attempts": 1
                                    },
                                    {
                                      "$id": "57",
                                      "$type": "NINA.Sequencer.SequenceItem.Imaging.TakeExposure, NINA.Sequencer",
                                      "ExposureTime": 600.0,
                                      "Gain": -1,
                                      "Offset": -1,
                                      "Binning": {
                                        "$id": "58",
                                        "$type": "NINA.Core.Model.Equipment.BinningMode, NINA.Core",
                                        "X": 1,
                                        "Y": 1
                                      },
                                      "ImageType": "LIGHT",
                                      "ExposureCount": 0,
                                      "Parent": {
                                        "$ref": "48"
                                      },
                                      "ErrorBehavior": 0,
                                      "Attempts": 1
                                    }
                                  ]
                                },
                                "Triggers": {
                                  "$id": "59",
                                  "$type": "System.Collections.ObjectModel.ObservableCollection`1[[NINA.Sequencer.Trigger.ISequenceTrigger, NINA.Sequencer]], System.ObjectModel",
                                  "$values": [
                                    {
                                      "$id": "60",
                                      "$type": "NINA.Sequencer.Trigger.Guider.DitherAfterExposures, NINA.Sequencer",
                                      "AfterExposures": 0,
                                      "Parent": {
                                        "$ref": "48"
                                      },
                                      "TriggerRunner": {
                                        "$id": "61",
                                        "$type": "NINA.Sequencer.Container.SequentialContainer, NINA.Sequencer",
                                        "Strategy": {
                                          "$type": "NINA.Sequencer.Container.ExecutionStrategy.SequentialStrategy, NINA.Sequencer"
                                        },
                                        "Name": null,
                                        "Conditions": {
                                          "$id": "62",
                                          "$type": "System.Collections.ObjectModel.ObservableCollection`1[[NINA.Sequencer.Conditions.ISequenceCondition, NINA.Sequencer]], System.ObjectModel",
                                          "$values": []
                                        },
                                        "IsExpanded": true,
                                        "Items": {
                                          "$id": "63",
                                          "$type": "System.Collections.ObjectModel.ObservableCollection`1[[NINA.Sequencer.SequenceItem.ISequenceItem, NINA.Sequencer]], System.ObjectModel",
                                          "$values": [
                                            {
                                              "$id": "64",
                                              "$type": "NINA.Sequencer.SequenceItem.Guider.Dither, NINA.Sequencer",
                                              "Parent": {
                                                "$ref": "61"
                                              },
                                              "ErrorBehavior": 0,
                                              "Attempts": 1
                                            }
                                          ]
                                        },
                                        "Triggers": {
                                          "$id": "65",
                                          "$type": "System.Collections.ObjectModel.ObservableCollection`1[[NINA.Sequencer.Trigger.ISequenceTrigger, NINA.Sequencer]], System.ObjectModel",
                                          "$values": []
                                        },
                                        "Parent": null,
                                        "ErrorBehavior": 0,
                                        "Attempts": 1
                                      }
                                    }
                                  ]
                                },
                                "Parent": {
                                  "$ref": "45"
                                }
                              }
                            ]
                          },
                          "Triggers": {
                            "$id": "66",
                            "$type": "System.Collections.ObjectModel.ObservableCollection`1[[NINA.Sequencer.Trigger.ISequenceTrigger, NINA.Sequencer]], System.ObjectModel",
                            "$values": [
                              {
                                "$id": "67",
                                "$type": "NINA.Sequencer.Trigger.Autofocus.AutofocusAfterHFRIncreaseTrigger, NINA.Sequencer",
                                "Amount": 5.0,
                                "SampleSize": 10,
                                "Parent": {
                                  "$ref": "45"
                                },
                                "TriggerRunner": {
                                  "$id": "68",
                                  "$type": "NINA.Sequencer.Container.SequentialContainer, NINA.Sequencer",
                                  "Strategy": {
                                    "$type": "NINA.Sequencer.Container.ExecutionStrategy.SequentialStrategy, NINA.Sequencer"
                                  },
                                  "Name": null,
                                  "Conditions": {
                                    "$id": "69",
                                    "$type": "System.Collections.ObjectModel.ObservableCollection`1[[NINA.Sequencer.Conditions.ISequenceCondition, NINA.Sequencer]], System.ObjectModel",
                                    "$values": []
                                  },
                                  "IsExpanded": true,
                                  "Items": {
                                    "$id": "70",
                                    "$type": "System.Collections.ObjectModel.ObservableCollection`1[[NINA.Sequencer.SequenceItem.ISequenceItem, NINA.Sequencer]], System.ObjectModel",
                                    "$values": [
                                      {
                                        "$id": "71",
                                        "$type": "NINA.Sequencer.SequenceItem.Autofocus.RunAutofocus, NINA.Sequencer",
                                        "Parent": {
                                          "$ref": "68"
                                        },
                                        "ErrorBehavior": 0,
                                        "Attempts": 1
                                      }
                                    ]
                                  },
                                  "Triggers": {
                                    "$id": "72",
                                    "$type": "System.Collections.ObjectModel.ObservableCollection`1[[NINA.Sequencer.Trigger.ISequenceTrigger, NINA.Sequencer]], System.ObjectModel",
                                    "$values": []
                                  },
                                  "Parent": null,
                                  "ErrorBehavior": 0,
                                  "Attempts": 1
                                }
                              },
                              {
                                "$id": "73",
                                "$type": "NINA.Sequencer.Trigger.Autofocus.AutofocusAfterFilterChange, NINA.Sequencer",
                                "Parent": {
                                  "$ref": "45"
                                },
                                "TriggerRunner": {
                                  "$id": "74",
                                  "$type": "NINA.Sequencer.Container.SequentialContainer, NINA.Sequencer",
                                  "Strategy": {
                                    "$type": "NINA.Sequencer.Container.ExecutionStrategy.SequentialStrategy, NINA.Sequencer"
                                  },
                                  "Name": null,
                                  "Conditions": {
                                    "$id": "75",
                                    "$type": "System.Collections.ObjectModel.ObservableCollection`1[[NINA.Sequencer.Conditions.ISequenceCondition, NINA.Sequencer]], System.ObjectModel",
                                    "$values": []
                                  },
                                  "IsExpanded": true,
                                  "Items": {
                                    "$id": "76",
                                    "$type": "System.Collections.ObjectModel.ObservableCollection`1[[NINA.Sequencer.SequenceItem.ISequenceItem, NINA.Sequencer]], System.ObjectModel",
                                    "$values": [
                                      {
                                        "$id": "77",
                                        "$type": "NINA.Sequencer.SequenceItem.Autofocus.RunAutofocus, NINA.Sequencer",
                                        "Parent": {
                                          "$ref": "74"
                                        },
                                        "ErrorBehavior": 0,
                                        "Attempts": 1
                                      }
                                    ]
                                  },
                                  "Triggers": {
                                    "$id": "78",
                                    "$type": "System.Collections.ObjectModel.ObservableCollection`1[[NINA.Sequencer.Trigger.ISequenceTrigger, NINA.Sequencer]], System.ObjectModel",
                                    "$values": []
                                  },
                                  "Parent": null,
                                  "ErrorBehavior": 0,
                                  "Attempts": 1
                                }
                              },
                              {
                                "$id": "79",
                                "$type": "NINA.Sequencer.Trigger.Guider.DitherAfterExposures, NINA.Sequencer",
                                "AfterExposures": 1,
                                "Parent": {
                                  "$ref": "45"
                                },
                                "TriggerRunner": {
                                  "$id": "80",
                                  "$type": "NINA.Sequencer.Container.SequentialContainer, NINA.Sequencer",
                                  "Strategy": {
                                    "$type": "NINA.Sequencer.Container.ExecutionStrategy.SequentialStrategy, NINA.Sequencer"
                                  },
                                  "Name": null,
                                  "Conditions": {
                                    "$id": "81",
                                    "$type": "System.Collections.ObjectModel.ObservableCollection`1[[NINA.Sequencer.Conditions.ISequenceCondition, NINA.Sequencer]], System.ObjectModel",
                                    "$values": []
                                  },
                                  "IsExpanded": true,
                                  "Items": {
                                    "$id": "82",
                                    "$type": "System.Collections.ObjectModel.ObservableCollection`1[[NINA.Sequencer.SequenceItem.ISequenceItem, NINA.Sequencer]], System.ObjectModel",
                                    "$values": [
                                      {
                                        "$id": "83",
                                        "$type": "NINA.Sequencer.SequenceItem.Guider.Dither, NINA.Sequencer",
                                        "Parent": {
                                          "$ref": "80"
                                        },
                                        "ErrorBehavior": 0,
                                        "Attempts": 1
                                      }
                                    ]
                                  },
                                  "Triggers": {
                                    "$id": "84",
                                    "$type": "System.Collections.ObjectModel.ObservableCollection`1[[NINA.Sequencer.Trigger.ISequenceTrigger, NINA.Sequencer]], System.ObjectModel",
                                    "$values": []
                                  },
                                  "Parent": null,
                                  "ErrorBehavior": 0,
                                  "Attempts": 1
                                }
                              }
                            ]
                          },
                          "Parent": {
                            "$ref": "30"
                          },
                          "ErrorBehavior": 0,
                          "Attempts": 1
                        }
                      ]
                    },
                    "Triggers": {
                      "$id": "85",
                      "$type": "System.Collections.ObjectModel.ObservableCollection`1[[NINA.Sequencer.Trigger.ISequenceTrigger, NINA.Sequencer]], System.ObjectModel",
                      "$values": [
                        {
                          "$id": "86",
                          "$type": "NINA.Sequencer.Trigger.MeridianFlip.MeridianFlipTrigger, NINA.Sequencer",
                          "Parent": {
                            "$ref": "30"
                          },
                          "TriggerRunner": {
                            "$id": "87",
                            "$type": "NINA.Sequencer.Container.SequentialContainer, NINA.Sequencer",
                            "Strategy": {
                              "$type": "NINA.Sequencer.Container.ExecutionStrategy.SequentialStrategy, NINA.Sequencer"
                            },
                            "Name": null,
                            "Conditions": {
                              "$id": "88",
                              "$type": "System.Collections.ObjectModel.ObservableCollection`1[[NINA.Sequencer.Conditions.ISequenceCondition, NINA.Sequencer]], System.ObjectModel",
                              "$values": []
                            },
                            "IsExpanded": true,
                            "Items": {
                              "$id": "89",
                              "$type": "System.Collections.ObjectModel.ObservableCollection`1[[NINA.Sequencer.SequenceItem.ISequenceItem, NINA.Sequencer]], System.ObjectModel",
                              "$values": []
                            },
                            "Triggers": {
                              "$id": "90",
                              "$type": "System.Collections.ObjectModel.ObservableCollection`1[[NINA.Sequencer.Trigger.ISequenceTrigger, NINA.Sequencer]], System.ObjectModel",
                              "$values": []
                            },
                            "Parent": null,
                            "ErrorBehavior": 0,
                            "Attempts": 1
                          }
                        },
                        {
                          "$id": "91",
                          "$type": "NINA.Sequencer.Trigger.Guider.RestoreGuiding, NINA.Sequencer",
                          "Parent": {
                            "$ref": "30"
                          },
                          "TriggerRunner": {
                            "$id": "92",
                            "$type": "NINA.Sequencer.Container.SequentialContainer, NINA.Sequencer",
                            "Strategy": {
                              "$type": "NINA.Sequencer.Container.ExecutionStrategy.SequentialStrategy, NINA.Sequencer"
                            },
                            "Name": null,
                            "Conditions": {
                              "$id": "93",
                              "$type": "System.Collections.ObjectModel.ObservableCollection`1[[NINA.Sequencer.Conditions.ISequenceCondition, NINA.Sequencer]], System.ObjectModel",
                              "$values": []
                            },
                            "IsExpanded": true,
                            "Items": {
                              "$id": "94",
                              "$type": "System.Collections.ObjectModel.ObservableCollection`1[[NINA.Sequencer.SequenceItem.ISequenceItem, NINA.Sequencer]], System.ObjectModel",
                              "$values": [
                                {
                                  "$id": "95",
                                  "$type": "NINA.Sequencer.SequenceItem.Guider.StartGuiding, NINA.Sequencer",
                                  "ForceCalibration": false,
                                  "Parent": {
                                    "$ref": "92"
                                  },
                                  "ErrorBehavior": 0,
                                  "Attempts": 1
                                }
                              ]
                            },
                            "Triggers": {
                              "$id": "96",
                              "$type": "System.Collections.ObjectModel.ObservableCollection`1[[NINA.Sequencer.Trigger.ISequenceTrigger, NINA.Sequencer]], System.ObjectModel",
                              "$values": []
                            },
                            "Parent": null,
                            "ErrorBehavior": 0,
                            "Attempts": 1
                          }
                        },
                        {
                          "$id": "97",
                          "$type": "NINA.Sequencer.Trigger.Platesolving.CenterAfterDriftTrigger, NINA.Sequencer",
                          "Coordinates": {
                            "$id": "98",
                            "$type": "NINA.Astrometry.InputCoordinates, NINA.Astrometry",
                            "RAHours": 22,
                            "RAMinutes": 30,
                            "RASeconds": 16.10427,
                            "NegativeDec": false,
                            "DecDegrees": 69,
                            "DecMinutes": 39,
                            "DecSeconds": 43.42609
                          },
                          "DistanceArcMinutes": 1.0,
                          "AfterExposures": 5,
                          "Parent": {
                            "$ref": "30"
                          },
                          "TriggerRunner": {
                            "$id": "99",
                            "$type": "NINA.Sequencer.Container.SequentialContainer, NINA.Sequencer",
                            "Strategy": {
                              "$type": "NINA.Sequencer.Container.ExecutionStrategy.SequentialStrategy, NINA.Sequencer"
                            },
                            "Name": null,
                            "Conditions": {
                              "$id": "100",
                              "$type": "System.Collections.ObjectModel.ObservableCollection`1[[NINA.Sequencer.Conditions.ISequenceCondition, NINA.Sequencer]], System.ObjectModel",
                              "$values": []
                            },
                            "IsExpanded": true,
                            "Items": {
                              "$id": "101",
                              "$type": "System.Collections.ObjectModel.ObservableCollection`1[[NINA.Sequencer.SequenceItem.ISequenceItem, NINA.Sequencer]], System.ObjectModel",
                              "$values": []
                            },
                            "Triggers": {
                              "$id": "102",
                              "$type": "System.Collections.ObjectModel.ObservableCollection`1[[NINA.Sequencer.Trigger.ISequenceTrigger, NINA.Sequencer]], System.ObjectModel",
                              "$values": []
                            },
                            "Parent": null,
                            "ErrorBehavior": 0,
                            "Attempts": 1
                          }
                        },
                        {
                          "$id": "103",
                          "$type": "WhenPlugin.When.WhenUnsafe, WhenPlugin",
                          "Instructions": {
                            "$id": "104",
                            "$type": "WhenPlugin.When.IfContainer, WhenPlugin",
                            "Strategy": {
                              "$type": "NINA.Sequencer.Container.ExecutionStrategy.SequentialStrategy, NINA.Sequencer"
                            },
                            "Name": "When Becomes Unsafe",
                            "Conditions": {
                              "$id": "105",
                              "$type": "System.Collections.ObjectModel.ObservableCollection`1[[NINA.Sequencer.Conditions.ISequenceCondition, NINA.Sequencer]], System.ObjectModel",
                              "$values": []
                            },
                            "IsExpanded": true,
                            "Items": {
                              "$id": "106",
                              "$type": "System.Collections.ObjectModel.ObservableCollection`1[[NINA.Sequencer.SequenceItem.ISequenceItem, NINA.Sequencer]], System.ObjectModel",
                              "$values": [
                                {
                                  "$id": "107",
                                  "$type": "NINA.Sequencer.SequenceItem.Guider.StopGuiding, NINA.Sequencer",
                                  "Parent": {
                                    "$ref": "104"
                                  },
                                  "ErrorBehavior": 0,
                                  "Attempts": 1
                                },
                                {
                                  "$id": "108",
                                  "$type": "NINA.Sequencer.SequenceItem.Telescope.FindHome, NINA.Sequencer",
                                  "Parent": {
                                    "$ref": "104"
                                  },
                                  "ErrorBehavior": 0,
                                  "Attempts": 1
                                },
                                {
                                  "$id": "109",
                                  "$type": "WhenPlugin.When.OnceSafe, WhenPlugin",
                                  "Condition": null,
                                  "Instructions": {
                                    "$id": "110",
                                    "$type": "WhenPlugin.When.IfContainer, WhenPlugin",
                                    "Strategy": {
                                      "$type": "NINA.Sequencer.Container.ExecutionStrategy.SequentialStrategy, NINA.Sequencer"
                                    },
                                    "Name": null,
                                    "Conditions": {
                                      "$id": "111",
                                      "$type": "System.Collections.ObjectModel.ObservableCollection`1[[NINA.Sequencer.Conditions.ISequenceCondition, NINA.Sequencer]], System.ObjectModel",
                                      "$values": [
                                        {
                                          "$id": "112",
                                          "$type": "NINA.Sequencer.Conditions.LoopCondition, NINA.Sequencer",
                                          "CompletedIterations": 0,
                                          "Iterations": 1,
                                          "Parent": {
                                            "$ref": "110"
                                          }
                                        },
                                        {
                                          "$id": "113",
                                          "$type": "NINA.Sequencer.Conditions.SafetyMonitorCondition, NINA.Sequencer",
                                          "Parent": {
                                            "$ref": "110"
                                          }
                                        }
                                      ]
                                    },
                                    "IsExpanded": true,
                                    "Items": {
                                      "$id": "114",
                                      "$type": "System.Collections.ObjectModel.ObservableCollection`1[[NINA.Sequencer.SequenceItem.ISequenceItem, NINA.Sequencer]], System.ObjectModel",
                                      "$values": [
                                        {
                                          "$id": "115",
                                          "$type": "NINA.Sequencer.SequenceItem.Telescope.FindHome, NINA.Sequencer",
                                          "Parent": {
                                            "$ref": "110"
                                          },
                                          "ErrorBehavior": 0,
                                          "Attempts": 1
                                        },
                                        {
                                          "$id": "116",
                                          "$type": "NINA.Sequencer.SequenceItem.Platesolving.Center, NINA.Sequencer",
                                          "Inherited": true,
                                          "Coordinates": {
                                            "$id": "117",
                                            "$type": "NINA.Astrometry.InputCoordinates, NINA.Astrometry",
                                            "RAHours": 22,
                                            "RAMinutes": 30,
                                            "RASeconds": 16.10427,
                                            "NegativeDec": false,
                                            "DecDegrees": 69,
                                            "DecMinutes": 39,
                                            "DecSeconds": 43.42609
                                          },
                                          "Parent": {
                                            "$ref": "110"
                                          },
                                          "ErrorBehavior": 0,
                                          "Attempts": 1
                                        },
                                        {
                                          "$id": "118",
                                          "$type": "NINA.Sequencer.SequenceItem.Guider.StartGuiding, NINA.Sequencer",
                                          "ForceCalibration": false,
                                          "Parent": {
                                            "$ref": "110"
                                          },
                                          "ErrorBehavior": 0,
                                          "Attempts": 1
                                        },
                                        {
                                          "$id": "119",
                                          "$type": "NINA.Sequencer.SequenceItem.Autofocus.RunAutofocus, NINA.Sequencer",
                                          "Parent": {
                                            "$ref": "110"
                                          },
                                          "ErrorBehavior": 0,
                                          "Attempts": 1
                                        }
                                      ]
                                    },
                                    "Triggers": {
                                      "$id": "120",
                                      "$type": "System.Collections.ObjectModel.ObservableCollection`1[[NINA.Sequencer.Trigger.ISequenceTrigger, NINA.Sequencer]], System.ObjectModel",
                                      "$values": []
                                    },
                                    "Parent": {
                                      "$ref": "104"
                                    },
                                    "ErrorBehavior": 0,
                                    "Attempts": 1
                                  },
                                  "Parent": {
                                    "$ref": "104"
                                  },
                                  "ErrorBehavior": 0,
                                  "Attempts": 1
                                }
                              ]
                            },
                            "Triggers": {
                              "$id": "121",
                              "$type": "System.Collections.ObjectModel.ObservableCollection`1[[NINA.Sequencer.Trigger.ISequenceTrigger, NINA.Sequencer]], System.ObjectModel",
                              "$values": []
                            },
                            "Parent": {
                              "$ref": "30"
                            },
                            "ErrorBehavior": 0,
                            "Attempts": 1
                          },
                          "Interrupt": true,
                          "Parent": {
                            "$ref": "30"
                          },
                          "TriggerRunner": {
                            "$id": "122",
                            "$type": "NINA.Sequencer.Container.SequentialContainer, NINA.Sequencer",
                            "Strategy": {
                              "$type": "NINA.Sequencer.Container.ExecutionStrategy.SequentialStrategy, NINA.Sequencer"
                            },
                            "Name": null,
                            "Conditions": {
                              "$id": "123",
                              "$type": "System.Collections.ObjectModel.ObservableCollection`1[[NINA.Sequencer.Conditions.ISequenceCondition, NINA.Sequencer]], System.ObjectModel",
                              "$values": []
                            },
                            "IsExpanded": true,
                            "Items": {
                              "$id": "124",
                              "$type": "System.Collections.ObjectModel.ObservableCollection`1[[NINA.Sequencer.SequenceItem.ISequenceItem, NINA.Sequencer]], System.ObjectModel",
                              "$values": []
                            },
                            "Triggers": {
                              "$id": "125",
                              "$type": "System.Collections.ObjectModel.ObservableCollection`1[[NINA.Sequencer.Trigger.ISequenceTrigger, NINA.Sequencer]], System.ObjectModel",
                              "$values": []
                            },
                            "Parent": null,
                            "ErrorBehavior": 0,
                            "Attempts": 1
                          }
                        }
                      ]
                    },
                    "Parent": {
                      "$ref": "25"
                    },
                    "ErrorBehavior": 0,
                    "Attempts": 1
                  }
                ]
              },
              "Triggers": {
                "$id": "126",
                "$type": "System.Collections.ObjectModel.ObservableCollection`1[[NINA.Sequencer.Trigger.ISequenceTrigger, NINA.Sequencer]], System.ObjectModel",
                "$values": []
              },
              "Parent": {
                "$ref": "22"
              },
              "ErrorBehavior": 0,
              "Attempts": 1
            }
          ]
        },
        "Triggers": {
          "$id": "127",
          "$type": "System.Collections.ObjectModel.ObservableCollection`1[[NINA.Sequencer.Trigger.ISequenceTrigger, NINA.Sequencer]], System.ObjectModel",
          "$values": []
        },
        "Parent": {
          "$ref": "1"
        },
        "ErrorBehavior": 0,
        "Attempts": 1
      },
      {
        "$id": "128",
        "$type": "NINA.Sequencer.Container.EndAreaContainer, NINA.Sequencer",
        "Strategy": {
          "$type": "NINA.Sequencer.Container.ExecutionStrategy.SequentialStrategy, NINA.Sequencer"
        },
        "Name": "End",
        "Conditions": {
          "$id": "129",
          "$type": "System.Collections.ObjectModel.ObservableCollection`1[[NINA.Sequencer.Conditions.ISequenceCondition, NINA.Sequencer]], System.ObjectModel",
          "$values": []
        },
        "IsExpanded": true,
        "Items": {
          "$id": "130",
          "$type": "System.Collections.ObjectModel.ObservableCollection`1[[NINA.Sequencer.SequenceItem.ISequenceItem, NINA.Sequencer]], System.ObjectModel",
          "$values": [
            {
              "$id": "131",
              "$type": "NINA.Sequencer.Container.SequentialContainer, NINA.Sequencer",
              "Strategy": {
                "$type": "NINA.Sequencer.Container.ExecutionStrategy.SequentialStrategy, NINA.Sequencer"
              },
              "Name": "Sequence End",
              "Conditions": {
                "$id": "132",
                "$type": "System.Collections.ObjectModel.ObservableCollection`1[[NINA.Sequencer.Conditions.ISequenceCondition, NINA.Sequencer]], System.ObjectModel",
                "$values": []
              },
              "IsExpanded": true,
              "Items": {
                "$id": "133",
                "$type": "System.Collections.ObjectModel.ObservableCollection`1[[NINA.Sequencer.SequenceItem.ISequenceItem, NINA.Sequencer]], System.ObjectModel",
                "$values": [
                  {
                    "$id": "134",
                    "$type": "NINA.Sequencer.Container.ParallelContainer, NINA.Sequencer",
                    "Strategy": {
                      "$type": "NINA.Sequencer.Container.ExecutionStrategy.ParallelStrategy, NINA.Sequencer"
                    },
                    "Name": "Parallel End of Sequence Instructions",
                    "Conditions": {
                      "$id": "135",
                      "$type": "System.Collections.ObjectModel.ObservableCollection`1[[NINA.Sequencer.Conditions.ISequenceCondition, NINA.Sequencer]], System.ObjectModel",
                      "$values": []
                    },
                    "IsExpanded": true,
                    "Items": {
                      "$id": "136",
                      "$type": "System.Collections.ObjectModel.ObservableCollection`1[[NINA.Sequencer.SequenceItem.ISequenceItem, NINA.Sequencer]], System.ObjectModel",
                      "$values": [
                        {
                          "$id": "137",
                          "$type": "NINA.Sequencer.SequenceItem.Telescope.FindHome, NINA.Sequencer",
                          "Parent": {
                            "$ref": "134"
                          },
                          "ErrorBehavior": 0,
                          "Attempts": 1
                        },
                        {
                          "$id": "138",
                          "$type": "NINA.Sequencer.SequenceItem.Camera.WarmCamera, NINA.Sequencer",
                          "Duration": 0.0,
                          "Parent": {
                            "$ref": "134"
                          },
                          "ErrorBehavior": 0,
                          "Attempts": 1
                        },
                        {
                          "$id": "139",
                          "$type": "NINA.Sequencer.SequenceItem.Guider.StopGuiding, NINA.Sequencer",
                          "Parent": {
                            "$ref": "134"
                          },
                          "ErrorBehavior": 0,
                          "Attempts": 1
                        }
                      ]
                    },
                    "Triggers": {
                      "$id": "140",
                      "$type": "System.Collections.ObjectModel.ObservableCollection`1[[NINA.Sequencer.Trigger.ISequenceTrigger, NINA.Sequencer]], System.ObjectModel",
                      "$values": []
                    },
                    "Parent": {
                      "$ref": "131"
                    },
                    "ErrorBehavior": 0,
                    "Attempts": 1
                  }
                ]
              },
              "Triggers": {
                "$id": "141",
                "$type": "System.Collections.ObjectModel.ObservableCollection`1[[NINA.Sequencer.Trigger.ISequenceTrigger, NINA.Sequencer]], System.ObjectModel",
                "$values": []
              },
              "Parent": {
                "$ref": "128"
              },
              "ErrorBehavior": 0,
              "Attempts": 1
            }
          ]
        },
        "Triggers": {
          "$id": "142",
          "$type": "System.Collections.ObjectModel.ObservableCollection`1[[NINA.Sequencer.Trigger.ISequenceTrigger, NINA.Sequencer]], System.ObjectModel",
          "$values": []
        },
        "Parent": {
          "$ref": "1"
        },
        "ErrorBehavior": 0,
        "Attempts": 1
      }
    ]
  },
  "Triggers": {
    "$id": "143",
    "$type": "System.Collections.ObjectModel.ObservableCollection`1[[NINA.Sequencer.Trigger.ISequenceTrigger, NINA.Sequencer]], System.ObjectModel",
    "$values": []
  },
  "Parent": null,
  "ErrorBehavior": 0,
  "Attempts": 1
}